LICENSE
snakypy/__init__.py
snakypy-0.4.0.dist-info/LICENSE
snakypy-0.4.0.dist-info/WHEEL
snakypy-0.4.0.dist-info/METADATA
snakypy-0.4.0.dist-info/RECORD
